strongarm/__init__.py
strongarm/common.py
strongarm/resources.py
stronglib-0.3.0.dist-info/METADATA
stronglib-0.3.0.dist-info/RECORD
stronglib-0.3.0.dist-info/WHEEL
stronglib-0.3.0.dist-info/top_level.txt
tasks/__init__.py
