Metadata-Version: 2.1
Name: stronglib
Version: 0.3.0
Summary: A Python library for strongarm.io API
Home-page: https://dnswatch.watchguard.com
Author: Percipient Networks, LLC
Author-email: support@strongarm.io
License: Apache 2.0
Download-URL: https://github.com/percipient/stronglib
Platform: UNKNOWN
Classifier: Development Status :: 4 - Beta
Classifier: Programming Language :: Python
Classifier: Programming Language :: Python :: 2
Classifier: Programming Language :: Python :: 2.7
Classifier: Programming Language :: Python :: 3
Classifier: Programming Language :: Python :: 3.4
Classifier: Programming Language :: Python :: 3.5
Classifier: Programming Language :: Python :: 3.6
Classifier: Programming Language :: Python :: 3.7
Classifier: Intended Audience :: Developers
Classifier: License :: OSI Approved :: Apache Software License
Classifier: Topic :: Internet :: WWW/HTTP
Classifier: Topic :: Software Development :: Libraries
Classifier: Topic :: System :: Networking
Requires-Dist: requests (==2.19.1)
Requires-Dist: six (==1.11.0)
